deployman/__init__.py
deployman/bootstrap.py
deployman/cli.py
deployman/models.py
deployman/storage.py
deployman/commands/service.py
deployman/commands/targets.py
deployman/connectors/__init__.py
deployman/connectors/base.py
deployman/connectors/factory.py
deployman/connectors/local.py
deployman/connectors/ssh.py
deployman/deployers/compose_deployer.py
deployman/services/backup_service.py
deployman/services/deploy_service.py
deployman/services/service.py
deployman/services/targets_service.py
deployman/toolbox/filesystem.py
deployman_cli-0.1.2.dist-info/METADATA
deployman_cli-0.1.2.dist-info/WHEEL
deployman_cli-0.1.2.dist-info/entry_points.txt
deployman_cli-0.1.2.dist-info/top_level.txt
deployman_cli-0.1.2.dist-info/RECORD
