Metadata-Version: 2.4
Name: deployman-cli
Version: 0.1.2
Summary: CLI skeleton for managing deployment targets with pluggable connectors
Requires-Python: <4.0,>=3.10
Requires-Dist: typer>=0.12
Requires-Dist: pydantic>=2
Requires-Dist: PyYAML>=6
Requires-Dist: paramiko>=3
Requires-Dist: rich>=13
Requires-Dist: filelock>=3
Requires-Dist: kink==0.8.1
